AUTHORS
CHANGELOG.md
LICENSE
MANIFEST.in
README.md
setup.py
d3cryp7/__init__.py
d3cryp7/__main__.py
d3cryp7/image.py
d3cryp7.py.egg-info/PKG-INFO
d3cryp7.py.egg-info/SOURCES.txt
d3cryp7.py.egg-info/dependency_links.txt
d3cryp7.py.egg-info/entry_points.txt
d3cryp7.py.egg-info/not-zip-safe
d3cryp7.py.egg-info/requires.txt
d3cryp7.py.egg-info/top_level.txt
d3cryp7/blueprints/__init__.py
d3cryp7/blueprints/activity.py
d3cryp7/blueprints/api.py
d3cryp7/blueprints/config.py
d3cryp7/blueprints/__pycache__/__init__.cpython-35.pyc
d3cryp7/blueprints/__pycache__/activity.cpython-35.pyc
d3cryp7/blueprints/__pycache__/api.cpython-35.pyc
d3cryp7/blueprints/__pycache__/config.cpython-35.pyc
d3cryp7/templates/activity.html
d3cryp7/templates/api.html
d3cryp7/templates/config.html
d3cryp7/templates/index.html
docs/api.md
docs/image.md
docs/wiki/Home.md
tests/__init__.py
tests/api.py
tests/image.py