Metadata-Version: 1.1
Name: d3cryp7.py
Version: 0.5.1
Summary: A Python module for image analysis and recognition
Home-page: https://bitbucket.org/bkvaluemeal/d3cryp7.py
Author: Justin Willis
Author-email: sirJustin.Willis@gmail.com
License: ISC License
Keywords: image analysis
Platform: UNKNOWN
Classifier: Development Status :: 1 - Planning
Classifier: Environment :: Web Environment
Classifier: Framework :: Flask
Classifier: Intended Audience :: Developers
Classifier: License :: OSI Approved :: ISC License (ISCL)
Classifier: Operating System :: OS Independent
Classifier: Programming Language :: Python :: 3
Classifier: Topic :: Scientific/Engineering :: Image Recognition
